bench/__init__.py
bench/cli.py
bench/py.typed
bench/reporter.py
bench/run.py
bench/secrets.py
bench/utils.py
bench/harness/__init__.py
bench/harness/client.py
bench/harness/config.py
bench/harness/csv_writer.py
bench/harness/evaluate.py
bench/harness/metrics.py
bench/harness/runner.py
onetool/__init__.py
onetool/cli.py
onetool/py.typed
ot/__init__.py
ot/__main__.py
ot/_cli.py
ot/_tui.py
ot/decorators.py
ot/http_client.py
ot/meta.py
ot/paths.py
ot/prompts.py
ot/py.typed
ot/server.py
ot/support.py
ot/tools.py
ot/config/__init__.py
ot/config/dynamic.py
ot/config/loader.py
ot/config/mcp.py
ot/config/secrets.py
ot/config/tool_config.py
ot/config/defaults/bench.yaml
ot/config/defaults/onetool.yaml
ot/config/defaults/prompts.yaml
ot/config/defaults/servers.yaml
ot/config/defaults/snippets.yaml
ot/config/defaults/diagram-templates/api-flow.mmd
ot/config/defaults/diagram-templates/c4-context.puml
ot/config/defaults/diagram-templates/class-diagram.mmd
ot/config/defaults/diagram-templates/feature-mindmap.mmd
ot/config/defaults/diagram-templates/microservices.d2
ot/config/defaults/diagram-templates/project-gantt.mmd
ot/config/defaults/diagram-templates/state-machine.mmd
ot/config/defaults/tool_templates/__init__.py
ot/config/defaults/tool_templates/extension.py
ot/config/defaults/tool_templates/isolated.py
ot/config/global_templates/__init__.py
ot/config/global_templates/bench-secrets-template.yaml
ot/config/global_templates/bench.yaml
ot/config/global_templates/onetool.yaml
ot/config/global_templates/secrets-template.yaml
ot/config/global_templates/servers.yaml
ot/config/global_templates/snippets.yaml
ot/executor/__init__.py
ot/executor/base.py
ot/executor/fence_processor.py
ot/executor/linter.py
ot/executor/pack_proxy.py
ot/executor/param_resolver.py
ot/executor/pep723.py
ot/executor/result_store.py
ot/executor/runner.py
ot/executor/simple.py
ot/executor/tool_loader.py
ot/executor/validator.py
ot/executor/worker_pool.py
ot/executor/worker_proxy.py
ot/logging/__init__.py
onetool_mcp-1.0.0b1.dist-info/METADATA
onetool_mcp-1.0.0b1.dist-info/WHEEL
onetool_mcp-1.0.0b1.dist-info/entry_points.txt
onetool_mcp-1.0.0b1.dist-info/licenses/LICENSE.txt
onetool_mcp-1.0.0b1.dist-info/licenses/NOTICE.txt
onetool_mcp-1.0.0b1.dist-info/RECORD
