Metadata-Version: 2.4
Name: onetool-mcp
Version: 1.0.0b1
Summary: One MCP, unlimited tools.
Project-URL: Homepage, https://github.com/beycom/onetool
Project-URL: Repository, https://github.com/beycom/onetool
Project-URL: Documentation, https://onetool.beycom.online
Project-URL: Issues, https://github.com/beycom/onetool/issues
Author-email: Gavin Las <beycom99@gmail.com>
License: GPL-3.0
License-File: LICENSE.txt
License-File: NOTICE.txt
Keywords: agents,code-execution,context-rot,llm,mcp,mcp-server,model-context-protocol,token-efficiency,tools
Classifier: Development Status :: 4 - Beta
Classifier: Intended Audience :: Developers
Classifier: License :: OSI Approved :: GNU General Public License v3 (GPLv3)
Classifier: Programming Language :: Python :: 3
Classifier: Programming Language :: Python :: 3.11
Classifier: Programming Language :: Python :: 3.12
Classifier: Topic :: Scientific/Engineering :: Artificial Intelligence
Classifier: Typing :: Typed
Requires-Python: >=3.11
Requires-Dist: aiofiles>=25.1.0
Requires-Dist: docstring-parser>=0.17
Requires-Dist: duckdb>=1.4.3
Requires-Dist: fastmcp>=2.14.4
Requires-Dist: firecrawl>=4.13.4
Requires-Dist: google-genai>=1.60.0
Requires-Dist: httpx>=0.28.1
Requires-Dist: jinja2>=3.1.6
Requires-Dist: loguru>=0.7.3
Requires-Dist: mcp>=1.26.0
Requires-Dist: openai>=2.15.0
Requires-Dist: openpyxl>=3.1.5
Requires-Dist: pillow>=12.1.0
Requires-Dist: pydantic-settings>=2.12.0
Requires-Dist: pydantic>=2.12.5
Requires-Dist: pymupdf>=1.26.7
Requires-Dist: python-docx>=1.2.0
Requires-Dist: python-pptx>=1.0.2
Requires-Dist: pyyaml>=6.0.3
Requires-Dist: questionary>=2.1.1
Requires-Dist: rich>=14.3.1
Requires-Dist: sqlalchemy>=2.0.46
Requires-Dist: trafilatura>=2.0.0
Requires-Dist: typer>=0.21.1
Provides-Extra: file
Requires-Dist: send2trash>=2.1.0; extra == 'file'
